bootest/VERSION
bootest/__init__.py
bootest/_bootest.pyi
bootest/_bootest.so
bootest-0.0.1.dist-info/METADATA
bootest-0.0.1.dist-info/WHEEL
bootest-0.0.1.dist-info/top_level.txt
bootest-0.0.1.dist-info/RECORD
